exams2anki.py
exams2anki-1.3.1.data/data/template/backside.html
exams2anki-1.3.1.data/data/template/frontside.html
exams2anki-1.3.1.data/data/template/style.css
exams2anki-1.3.1.dist-info/LICENSE
exams2anki-1.3.1.dist-info/METADATA
exams2anki-1.3.1.dist-info/WHEEL
exams2anki-1.3.1.dist-info/entry_points.txt
exams2anki-1.3.1.dist-info/top_level.txt
exams2anki-1.3.1.dist-info/RECORD
